{
	"tile": {
		"TileID": "1",
		"GameID": "1",
		"Name": "Abandoned Room",
		"Floor": "Basement",
		"State": "Not Played"
	}
	"tile": {
		"TileID": "2",
		"GameID": "1",
		"Name": "Attic",
		"Floor": "Upper",
		"State": "Not Played"
	}
	"tile": {
		"TileID": "3",
		"GameID": "1",
		"Name": "Balcony",
		"Floor": "Upper",
		"State": "Not Played"
	}
	"tile": {
		"TileID": "4",
		"GameID": "1",
		"Name": "Ballroom",
		"Floor": "Ground",
		"State": "Not Played"
	}
	"tile": {
		"TileID": "5",
		"GameID": "1",
		"Name": "Basement Landing",
		"Floor": "Basement",
		"State": "Played"
	}
	"tile": {
		"TileID": "6",
		"GameID": "1",
		"Name": "Bedroom",
		"Floor": "Upper",
		"State": "Not Played"
	}
	"tile": {
		"TileID": "7",
		"GameID": "1",
		"Name": "Bloody Room",
		"Floor": "Ground",
		"State": "Not Played"
	}
	"tile": {
		"TileID": "8",
		"GameID": "1",
		"Name": "Catacombs",
		"Floor": "Basement",
		"State": "Not Played"
	}
	"tile": {
		"TileID": "9",
		"GameID": "1",
		"Name": "Chapel",
		"Floor": "Ground",
		"State": "Not Played"
	}
	"tile": {
		"TileID": "10",
		"GameID": "1",
		"Name": "Charred Room",
		"Floor": "Upper",
		"State": "Not Played"
	}
	"tile": {
		"TileID": "11",
		"GameID": "1",
		"Name": "Chasm",
		"Floor": "Basement",
		"State": "Not Played"
	}
	"tile": {
		"TileID": "12",
		"GameID": "1",
		"Name": "Coal Chute",
		"Floor": "Ground",
		"State": "Not Played"
	}
	"tile": {
		"TileID": "13",
		"GameID": "1",
		"Name": "Collapsed Room",
		"Floor": "Ground",
		"State": "Not Played"
	}
	"tile": {
		"TileID": "14",
		"GameID": "1",
		"Name": "Conservatory",
		"Floor": "Upper",
		"State": "Not Played"
	}
	"tile": {
		"TileID": "15",
		"GameID": "1",
		"Name": "Creaky Hallway",
		"Floor": "Ground",
		"State": "Not Played"
	}
	"tile": {
		"TileID": "16",
		"GameID": "1",
		"Name": "Crypt",
		"Floor": "Basement",
		"State": "Not Played"
	}
	"tile": {
		"TileID": "17",
		"GameID": "1",
		"Name": "Dining Room",
		"Floor": "Ground",
		"State": "Not Played"
	}
	"tile": {
		"TileID": "18",
		"GameID": "1",
		"Name": "Dusty Hallway",
		"Floor": "Upper",
		"State": "Not Played"
	}
	"tile": {
		"TileID": "19",
		"GameID": "1",
		"Name": "Entrance Hall",
		"Floor": "Ground",
		"State": "Played"
	}
	"tile": {
		"TileID": "20",
		"GameID": "1",
		"Name": "Foyer",
		"Floor": "Ground",
		"State": "Played"
	}
	"tile": {
		"TileID": "21",
		"GameID": "1",
		"Name": "Furnace Room",
		"Floor": "Basement",
		"State": "Not Played"
	}
	"tile": {
		"TileID": "22",
		"GameID": "1",
		"Name": "Gallery",
		"Floor": "Upper",
		"State": "Not Played"
	}
	"tile": {
		"TileID": "23",
		"GameID": "1",
		"Name": "Game Room",
		"Floor": "Upper",
		"State": "Not Played"
	}
	"tile": {
		"TileID": "24",
		"GameID": "1",
		"Name": "Gardens",
		"Floor": "Ground",
		"State": "Not Played"
	}
	"tile": {
		"TileID": "25",
		"GameID": "1",
		"Name": "Grand Staircase",
		"Floor": "Ground",
		"State": "Not Played"
	}
	"tile": {
		"TileID": "26",
		"GameID": "1",
		"Name": "Graveyard",
		"Floor": "Ground",
		"State": "Not Played"
	}
	"tile": {
		"TileID": "27",
		"GameID": "1",
		"Name": "Gymnasium",
		"Floor": "Basement",
		"State": "Not Played"
	}
	"tile": {
		"TileID": "28",
		"GameID": "1",
		"Name": "Junk Room",
		"Floor": "Basement",
		"State": "Not Played"
	}
	"tile": {
		"TileID": "29",
		"GameID": "1",
		"Name": "Kitchen",
		"Floor": "Ground",
		"State": "Not Played"
	}
	"tile": {
		"TileID": "30",
		"GameID": "1",
		"Name": "Larder",
		"Floor": "Basement",
		"State": "Not Played"
	}
	"tile": {
		"TileID": "31",
		"GameID": "1",
		"Name": "Library",
		"Floor": "Upper",
		"State": "Not Played"
	}
	"tile": {
		"TileID": "32",
		"GameID": "1",
		"Name": "Master Bedroom",
		"Floor": "Upper",
		"State": "Not Played"
	}
	"tile": {
		"TileID": "33",
		"GameID": "1",
		"Name": "Mystic Elevator",
		"Floor": "Ground",
		"State": "Not Played"
	}
	"tile": {
		"TileID": "34",
		"GameID": "1",
		"Name": "Operating Laboratory",
		"Floor": "Basement",
		"State": "Not Played"
	}
	"tile": {
		"TileID": "35",
		"GameID": "1",
		"Name": "Organ Room",
		"Floor": "Ground",
		"State": "Not Played"
	}
	"tile": {
		"TileID": "36",
		"GameID": "1",
		"Name": "Patio",
		"Floor": "Ground",
		"State": "Not Played"
	}
	"tile": {
		"TileID": "37",
		"GameID": "1",
		"Name": "Pentagram Chamber",
		"Floor": "Basement",
		"State": "Not Played"
	}
	"tile": {
		"TileID": "38",
		"GameID": "1",
		"Name": "Research Laboratory",
		"Floor": "Upper",
		"State": "Not Played"
	}
	"tile": {
		"TileID": "39",
		"GameID": "1",
		"Name": "Servants' Quarters",
		"Floor": "Upper",
		"State": "Not Played"
	}
	"tile": {
		"TileID": "40",
		"GameID": "1",
		"Name": "Stairs From Basement",
		"Floor": "Basement",
		"State": "Not Played"
	}
	"tile": {
		"TileID": "41",
		"GameID": "1",
		"Name": "Statuary Corridor",
		"Floor": "Basement",
		"State": "Not Played"
	}
	"tile": {
		"TileID": "42",
		"GameID": "1",
		"Name": "Storeroom",
		"Floor": "Upper",
		"State": "Not Played"
	}
	"tile": {
		"TileID": "43",
		"GameID": "1",
		"Name": "Tower",
		"Floor": "Upper",
		"State": "Not Played"
	}
	"tile": {
		"TileID": "44",
		"GameID": "1",
		"Name": "Underground Lake",
		"Floor": "Basement",
		"State": "Not Played"
	}
	"tile": {
		"TileID": "45",
		"GameID": "1",
		"Name": "Upper Landing",
		"Floor": "Upper",
		"State": "Played"
	}
	"tile": {
		"TileID": "46",
		"GameID": "1",
		"Name": "Vault",
		"Floor": "Basement",
		"State": "Not Played"
	}
	"tile": {
		"TileID": "47",
		"GameID": "1",
		"Name": "Wine Cellar",
		"Floor": "Basement",
		"State": "Not Played"
	}
	"tile": {
		"TileID": "48",
		"GameID": "2",
		"Name": "Abandoned Room",
		"Floor": "Basement",
		"State": "Played"
	}
	"tile": {
		"TileID": "49",
		"GameID": "2",
		"Name": "Attic",
		"Floor": "Upper",
		"State": "Played"
	}
	"tile": {
		"TileID": "50",
		"GameID": "2",
		"Name": "Balcony",
		"Floor": "Upper",
		"State": "Played"
	}
	"tile": {
		"TileID": "51",
		"GameID": "2",
		"Name": "Ballroom",
		"Floor": "Ground",
		"State": "Played"
	}
	"tile": {
		"TileID": "52",
		"GameID": "2",
		"Name": "Basement Landing",
		"Floor": "Basement",
		"State": "Played"
	}
	"tile": {
		"TileID": "53",
		"GameID": "2",
		"Name": "Bedroom",
		"Floor": "Upper",
		"State": "Played"
	}
	"tile": {
		"TileID": "54",
		"GameID": "2",
		"Name": "Bloody Room",
		"Floor": "Ground",
		"State": "Played"
	}
	"tile": {
		"TileID": "55",
		"GameID": "2",
		"Name": "Catacombs",
		"Floor": "Basement",
		"State": "Played"
	}
	"tile": {
		"TileID": "56",
		"GameID": "2",
		"Name": "Chapel",
		"Floor": "Ground",
		"State": "Played"
	}
	"tile": {
		"TileID": "57",
		"GameID": "2",
		"Name": "Charred Room",
		"Floor": "Upper",
		"State": "Played"
	}
	"tile": {
		"TileID": "58",
		"GameID": "2",
		"Name": "Chasm",
		"Floor": "Basement",
		"State": "Played"
	}
	"tile": {
		"TileID": "59",
		"GameID": "2",
		"Name": "Coal Chute",
		"Floor": "Ground",
		"State": "Played"
	}
	"tile": {
		"TileID": "60",
		"GameID": "2",
		"Name": "Collapsed Room",
		"Floor": "Ground",
		"State": "Played"
	}
	"tile": {
		"TileID": "61",
		"GameID": "2",
		"Name": "Conservatory",
		"Floor": "Upper",
		"State": "Played"
	}
	"tile": {
		"TileID": "62",
		"GameID": "2",
		"Name": "Creaky Hallway",
		"Floor": "Ground",
		"State": "Played"
	}
	"tile": {
		"TileID": "63",
		"GameID": "2",
		"Name": "Crypt",
		"Floor": "Basement",
		"State": "Played"
	}
	"tile": {
		"TileID": "64",
		"GameID": "2",
		"Name": "Dining Room",
		"Floor": "Ground",
		"State": "Played"
	}
	"tile": {
		"TileID": "65",
		"GameID": "2",
		"Name": "Dusty Hallway",
		"Floor": "Upper",
		"State": "Played"
	}
	"tile": {
		"TileID": "66",
		"GameID": "2",
		"Name": "Entrance Hall",
		"Floor": "Ground",
		"State": "Played"
	}
	"tile": {
		"TileID": "67",
		"GameID": "2",
		"Name": "Foyer",
		"Floor": "Ground",
		"State": "Played"
	}
	"tile": {
		"TileID": "68",
		"GameID": "2",
		"Name": "Furnace Room",
		"Floor": "Basement",
		"State": "Played"
	}
	"tile": {
		"TileID": "69",
		"GameID": "2",
		"Name": "Gallery",
		"Floor": "Upper",
		"State": "Played"
	}
	"tile": {
		"TileID": "70",
		"GameID": "2",
		"Name": "Game Room",
		"Floor": "Upper",
		"State": "Played"
	}
	"tile": {
		"TileID": "71",
		"GameID": "2",
		"Name": "Gardens",
		"Floor": "Ground",
		"State": "Played"
	}
	"tile": {
		"TileID": "72",
		"GameID": "2",
		"Name": "Grand Staircase",
		"Floor": "Ground",
		"State": "Played"
	}
	"tile": {
		"TileID": "73",
		"GameID": "2",
		"Name": "Graveyard",
		"Floor": "Ground",
		"State": "Played"
	}
	"tile": {
		"TileID": "74",
		"GameID": "2",
		"Name": "Gymnasium",
		"Floor": "Basement",
		"State": "Played"
	}
	"tile": {
		"TileID": "75",
		"GameID": "2",
		"Name": "Junk Room",
		"Floor": "Basement",
		"State": "Played"
	}
	"tile": {
		"TileID": "76",
		"GameID": "2",
		"Name": "Kitchen",
		"Floor": "Ground",
		"State": "Played"
	}
	"tile": {
		"TileID": "77",
		"GameID": "2",
		"Name": "Larder",
		"Floor": "Basement",
		"State": "Played"
	}
	"tile": {
		"TileID": "78",
		"GameID": "2",
		"Name": "Library",
		"Floor": "Upper",
		"State": "Played"
	}
	"tile": {
		"TileID": "79",
		"GameID": "2",
		"Name": "Master Bedroom",
		"Floor": "Upper",
		"State": "Played"
	}
	"tile": {
		"TileID": "80",
		"GameID": "2",
		"Name": "Mystic Elevator",
		"Floor": "Ground",
		"State": "Played"
	}
	"tile": {
		"TileID": "81",
		"GameID": "2",
		"Name": "Operating Laboratory",
		"Floor": "Basement",
		"State": "Played"
	}
	"tile": {
		"TileID": "82",
		"GameID": "2",
		"Name": "Organ Room",
		"Floor": "Ground",
		"State": "Played"
	}
	"tile": {
		"TileID": "83",
		"GameID": "2",
		"Name": "Patio",
		"Floor": "Ground",
		"State": "Played"
	}
	"tile": {
		"TileID": "84",
		"GameID": "2",
		"Name": "Pentagram Chamber",
		"Floor": "Basement",
		"State": "Played"
	}
	"tile": {
		"TileID": "85",
		"GameID": "2",
		"Name": "Research Laboratory",
		"Floor": "Upper",
		"State": "Played"
	}
	"tile": {
		"TileID": "86",
		"GameID": "2",
		"Name": "Servants' Quarters",
		"Floor": "Upper",
		"State": "Played"
	}
	"tile": {
		"TileID": "87",
		"GameID": "2",
		"Name": "Stairs From Basement",
		"Floor": "Basement",
		"State": "Played"
	}
	"tile": {
		"TileID": "88",
		"GameID": "2",
		"Name": "Statuary Corridor",
		"Floor": "Basement",
		"State": "Played"
	}
	"tile": {
		"TileID": "89",
		"GameID": "2",
		"Name": "Storeroom",
		"Floor": "Upper",
		"State": "Played"
	}
	"tile": {
		"TileID": "90",
		"GameID": "2",
		"Name": "Tower",
		"Floor": "Upper",
		"State": "Played"
	}
	"tile": {
		"TileID": "91",
		"GameID": "2",
		"Name": "Underground Lake",
		"Floor": "Basement",
		"State": "Played"
	}
	"tile": {
		"TileID": "92",
		"GameID": "2",
		"Name": "Upper Landing",
		"Floor": "Upper",
		"State": "Played"
	}
	"tile": {
		"TileID": "93",
		"GameID": "2",
		"Name": "Vault",
		"Floor": "Basement",
		"State": "Played"
	}
	"tile": {
		"TileID": "94",
		"GameID": "2",
		"Name": "Wine Cellar",
		"Floor": "Basement",
		"State": "Played"
	}
}